pentapy/__init__.pxd
pentapy/__init__.py
pentapy/_version.py
pentapy/core.py
pentapy/solver.cpython-39-x86_64-linux-gnu.so
pentapy/solver.pxd
pentapy/tools.py
pentapy-1.4.1.dist-info/METADATA
pentapy-1.4.1.dist-info/WHEEL
pentapy-1.4.1.dist-info/top_level.txt
pentapy-1.4.1.dist-info/RECORD
pentapy-1.4.1.dist-info/licenses/LICENSE
