Metadata-Version: 2.4
Name: pentapy
Version: 1.4.1
Summary: pentapy: A toolbox for pentadiagonal matrizes.
Author-email: Sebastian Müller <info@geostat-framework.org>
License-Expression: MIT
Project-URL: Homepage, https://github.com/GeoStat-Framework/pentapy
Project-URL: Documentation, https://pentapy.readthedocs.io
Project-URL: Source, https://github.com/GeoStat-Framework/pentapy
Project-URL: Tracker, https://github.com/GeoStat-Framework/pentapy/issues
Project-URL: Changelog, https://github.com/GeoStat-Framework/pentapy/blob/main/CHANGELOG.md
Project-URL: Conda-Forge, https://anaconda.org/conda-forge/pentapy
Classifier: Development Status :: 5 - Production/Stable
Classifier: Intended Audience :: Developers
Classifier: Intended Audience :: End Users/Desktop
Classifier: Intended Audience :: Science/Research
Classifier: Natural Language :: English
Classifier: Operating System :: Unix
Classifier: Programming Language :: Python
Classifier: Programming Language :: Python :: 3
Classifier: Programming Language :: Python :: 3.9
Classifier: Programming Language :: Python :: 3.10
Classifier: Programming Language :: Python :: 3.11
Classifier: Programming Language :: Python :: 3.12
Classifier: Programming Language :: Python :: 3.13
Classifier: Programming Language :: Python :: 3.14
Classifier: Programming Language :: Python :: 3 :: Only
Classifier: Topic :: Scientific/Engineering
Classifier: Topic :: Utilities
Requires-Python: >=3.9
License-File: LICENSE
Requires-Dist: numpy>=1.20.0
Provides-Extra: scipy
Requires-Dist: scipy; extra == "scipy"
Provides-Extra: umfpack
Requires-Dist: scikit-umfpack; extra == "umfpack"
Provides-Extra: all
Requires-Dist: scipy; extra == "all"
Requires-Dist: scikit-umfpack; extra == "all"
Provides-Extra: doc
Requires-Dist: myst_parser; extra == "doc"
Requires-Dist: scipy>=1.1.0; extra == "doc"
Requires-Dist: matplotlib>=3; extra == "doc"
Requires-Dist: perfplot<0.9; extra == "doc"
Requires-Dist: numpydoc>=1.1; extra == "doc"
Requires-Dist: sphinx>=7; extra == "doc"
Requires-Dist: sphinx-gallery>=0.8; extra == "doc"
Requires-Dist: sphinx-rtd-theme>=3; extra == "doc"
Provides-Extra: test
Requires-Dist: pytest-cov>=3; extra == "test"
Requires-Dist: Cython<3.1.0,>=3.0.10; extra == "test"
Provides-Extra: check
Requires-Dist: black>=24; extra == "check"
Requires-Dist: isort[colors]; extra == "check"
Requires-Dist: pylint; extra == "check"
Requires-Dist: cython-lint; extra == "check"
Dynamic: license-file
